jaraco/fabric/__init__.py
jaraco/fabric/__main__.py
jaraco/fabric/apt.py
jaraco/fabric/certs.py
jaraco/fabric/fabfile.py
jaraco/fabric/files.py
jaraco/fabric/mongod.service
jaraco/fabric/mongodb.py
jaraco/fabric/monkey.py
jaraco/fabric/python.py
jaraco/fabric/shell.py
jaraco/fabric/wrapper.py
jaraco_fabric-6.3.1.dist-info/LICENSE
jaraco_fabric-6.3.1.dist-info/METADATA
jaraco_fabric-6.3.1.dist-info/WHEEL
jaraco_fabric-6.3.1.dist-info/top_level.txt
jaraco_fabric-6.3.1.dist-info/RECORD
